./.gitignore
./CHANGELOG.md
./DEVELOPMENT.md
./LICENSE
./Makefile
./PKG-INFO
./README.md
./pyproject.toml
./uv.lock
./.github/workflows/ci.yml
./tests/conftest.py
./tests/test-mypy.ini
./tests/test_mypy_plugin.py
./tests/test_python_module.py
./tests/test_past_issues/test_4_mypy_cache/input.py
./tests/test_past_issues/test_4_mypy_cache/test_4_mypy_cache.py
./tests/test_past_issues/test_8_non_protocol_member/__init__.py
./tests/test_past_issues/test_8_non_protocol_member/input.py
./tests/test_past_issues/test_8_non_protocol_member/test_8_non_protocol_member.py
./tests/testcases/fails_for_non_protocols.py
./tests/testcases/function_return_type_happy_path.py
./tests/testcases/function_return_type_unhappy_path.py
./tests/testcases/in_generic_param_happy_path.py
./tests/testcases/in_generic_param_happy_path_covariant.py
./tests/testcases/in_generic_param_unhappy_path.py
./tests/testcases/multiple_params_happy_path.py
./tests/testcases/multiple_params_unhappy_path.py
./tests/testcases/protocol_extending_another_builder_happy_path.py
./tests/testcases/protocol_extending_another_builder_unhappy_path.py
./tests/testcases/protocol_extending_another_method_happy_path.py
./tests/testcases/protocol_extending_another_property_happy_path.py
./tools/prepare-pr-after-mypy-bump.sh
./typing_protocol_intersection/__init__.py
./typing_protocol_intersection/mypy_plugin.py
./typing_protocol_intersection/py.typed
./typing_protocol_intersection/types.py
typing_protocol_intersection-0.6.0.dist-info/METADATA
typing_protocol_intersection-0.6.0.dist-info/WHEEL
typing_protocol_intersection-0.6.0.dist-info/licenses/LICENSE
typing_protocol_intersection-0.6.0.dist-info/RECORD
