Metadata-Version: 2.4
Name: typing-protocol-intersection
Version: 0.6.0
Summary: Protocol intersection for mypy
Project-URL: Homepage, https://github.com/klausweiss/typing-protocol-intersection
Project-URL: Bug Tracker, https://github.com/klausweiss/typing-protocol-intersection/issues
License: MIT
License-File: LICENSE
Classifier: License :: OSI Approved :: MIT License
Classifier: Operating System :: OS Independent
Classifier: Programming Language :: Python :: 3
Classifier: Programming Language :: Python :: 3.10
Classifier: Programming Language :: Python :: 3.11
Classifier: Programming Language :: Python :: 3.12
Classifier: Programming Language :: Python :: 3.13
Classifier: Programming Language :: Python :: 3.14
Classifier: Typing :: Typed
Requires-Python: >=3.10
